ether/__init__.py
ether/cli.py
ether/local.py
ether/transaction.py
ether/utils.py
ether/wallet.py
ether_cli-0.1.11.dist-info/LICENSE.md
ether_cli-0.1.11.dist-info/METADATA
ether_cli-0.1.11.dist-info/WHEEL
ether_cli-0.1.11.dist-info/entry_points.txt
ether_cli-0.1.11.dist-info/top_level.txt
ether_cli-0.1.11.dist-info/RECORD
