Metadata-Version: 2.1
Name: ether-cli
Version: 0.1.11
Summary: Minimalistic wallet CLI for Ethereum
Home-page: https://github.com/0xver/ether
Author: Sam Larsen
License: MIT
Requires-Python: >=3.9
License-File: LICENSE.md
Requires-Dist: cryptography
Requires-Dist: mnemonic
Requires-Dist: hdwallet
Requires-Dist: web3
Requires-Dist: requests
